hmxlabs/sysinfo/__init__.py
hmxlabs/sysinfo/__main__.py
hmxlabs/sysinfo/sysinfo.py
hmxlabs.sysinfo-1.0.9.dist-info/METADATA
hmxlabs.sysinfo-1.0.9.dist-info/WHEEL
hmxlabs.sysinfo-1.0.9.dist-info/entry_points.txt
hmxlabs.sysinfo-1.0.9.dist-info/top_level.txt
hmxlabs.sysinfo-1.0.9.dist-info/RECORD
