Metadata-Version: 2.2
Name: hmxlabs.sysinfo
Version: 1.0.9
Summary: Package to get basic system information including CPU count, HT/SMT status, RAM and disk. Not doing anything special. Just uses psutil and py-cpuinfo
Author-email: HMx Labs <comms@hmxlabs.uk>
Project-URL: Homepage, https://github.com/hmxlabs/sysinfo/
Project-URL: HMxLabs, http://hmxlabs.uk
Classifier: Programming Language :: Python :: 3.10
Classifier: License :: OSI Approved :: MIT License
Classifier: Operating System :: OS Independent
Classifier: Environment :: Console
Classifier: Intended Audience :: Developers
Requires-Python: >=3.10
Requires-Dist: psutil~=6.1.1
Requires-Dist: py-cpuinfo==9.0.0
